frame/__init__.py
frame/framefile.py
frame/full.py
frame/nets_plugin.py
frame/simple.py
frame/simple_frames.py
frame/simple_nets.py
frame/frame_core/__init__.py
frame/frame_core/composer.py
frame/frame_core/exceptions.py
frame/frame_core/frames.py
frame/frame_core/funcs.py
frame/frame_core/plugins.py
frame/frame_core/plugins_system.py
frame/nets_core/__init__.py
frame/nets_core/crypto/__init__.py
frame/nets_core/crypto/bip39_worldlist.py
frame/nets_core/crypto/hashes.py
frame/nets_core/crypto/rand_system.py
frame/nets_core/hack/__init__.py
frame/nets_core/hack/gray.py
frame/nets_core/hack/white.py
frame/nets_core/secure/__init__.py
frame/nets_core/secure/data_security.py
frame/nets_core/utils/__init__.py
frame/utils/__init__.py
frame/utils/system.py
frame/utils/alternative/__init__.py
frame/utils/alternative/alt_math.py
frame/utils/alternative/alt_sys.py
unitests/__init__.py
unitests/test_composer.py
unitests/test_core.py
unitests/test_integration.py
unitests/test_performance.py
unitests/test_plugins.py
frame_fwl-0.5.6.5.dist-info/METADATA
frame_fwl-0.5.6.5.dist-info/WHEEL
frame_fwl-0.5.6.5.dist-info/entry_points.txt
frame_fwl-0.5.6.5.dist-info/top_level.txt
frame_fwl-0.5.6.5.dist-info/RECORD
