Metadata-Version: 2.4
Name: frame-fwl
Version: 0.5.6.5
Summary: The Frame - multitool framework.
Home-page: https://github.com/pt-main/frame
Author: pt
Author-email: kvantorium73.int@gmail.com
Keywords: frame,superglobal,context,context manager,framing,code generation,execution,nets,frames
Classifier: Development Status :: 3 - Alpha
Classifier: Intended Audience :: Developers
Classifier: License :: OSI Approved :: MIT License
Classifier: Programming Language :: Python :: 3.10
Classifier: Programming Language :: Python :: 3.11
Classifier: Programming Language :: Python :: 3.12
Classifier: Programming Language :: Python :: 3.13
Classifier: Programming Language :: Python :: 3.14
Classifier: Operating System :: OS Independent
Requires-Python: >=3.10
Requires-Dist: cryptography
Requires-Dist: requests
Dynamic: author
Dynamic: author-email
Dynamic: classifier
Dynamic: home-page
Dynamic: keywords
Dynamic: requires-dist
Dynamic: requires-python
Dynamic: summary
